webullsdktrade/__init__.py
webullsdktrade/api.py
webullsdktrade/grpc_api.py
webullsdktrade/common/__init__.py
webullsdktrade/common/account_type.py
webullsdktrade/common/category.py
webullsdktrade/common/combo_ticker_type.py
webullsdktrade/common/combo_type.py
webullsdktrade/common/currency.py
webullsdktrade/common/forbid_reason.py
webullsdktrade/common/instrument_type.py
webullsdktrade/common/markets.py
webullsdktrade/common/order_entrust_type.py
webullsdktrade/common/order_side.py
webullsdktrade/common/order_status.py
webullsdktrade/common/order_tif.py
webullsdktrade/common/order_type.py
webullsdktrade/common/trade_policy.py
webullsdktrade/common/trading_date_type.py
webullsdktrade/common/trailing_type.py
webullsdktrade/events/__init__.py
webullsdktrade/events/types.py
webullsdktrade/request/__init__.py
webullsdktrade/request/cancel_order_request.py
webullsdktrade/request/get_account_balance_request.py
webullsdktrade/request/get_account_position_details_request.py
webullsdktrade/request/get_account_positions_request.py
webullsdktrade/request/get_account_profile_request.py
webullsdktrade/request/get_app_subscriptions.py
webullsdktrade/request/get_open_orders_request.py
webullsdktrade/request/get_order_detail_request.py
webullsdktrade/request/get_today_orders_request.py
webullsdktrade/request/get_trade_calendar_request.py
webullsdktrade/request/get_trade_instrument_detail_request.py
webullsdktrade/request/get_trade_security_detail_request.py
webullsdktrade/request/get_tradeable_instruments_request.py
webullsdktrade/request/palce_order_request.py
webullsdktrade/request/place_order_request_v2.py
webullsdktrade/request/replace_order_request.py
webullsdktrade/request/replace_order_request_v2.py
webullsdktrade/request/v2/__init__.py
webullsdktrade/request/v2/cancel_option_request.py
webullsdktrade/request/v2/cancel_order_request.py
webullsdktrade/request/v2/get_account_balance_request.py
webullsdktrade/request/v2/get_account_list.py
webull_python_sdk_trade-0.1.18.dist-info/METADATA
webull_python_sdk_trade-0.1.18.dist-info/WHEEL
webull_python_sdk_trade-0.1.18.dist-info/top_level.txt
webull_python_sdk_trade-0.1.18.dist-info/RECORD
